jenkins_job_manager/__init__.py
jenkins_job_manager/cli.py
jenkins_job_manager/connect_config.py
jenkins_job_manager/core.py
jenkins_job_manager/j2_templates/default.j2
jenkins_job_manager/j2_templates/json.j2
jenkins_job_manager/j2_templates/raw_xml_import.j2
jenkins_job_manager/j2_templates/yaml.j2
jenkins_job_manager/raw_ext.py
jenkins_job_manager/xml_change.py
jenkins_job_manager-0.6.7.dist-info/entry_points.txt
jenkins_job_manager-0.6.7.dist-info/LICENSE
jenkins_job_manager-0.6.7.dist-info/WHEEL
jenkins_job_manager-0.6.7.dist-info/METADATA
jenkins_job_manager-0.6.7.dist-info/RECORD
