Metadata-Version: 2.1
Name: jenkins-job-manager
Version: 0.6.7
Summary: A terraform-like wrapper around JJB with some additional features.
Author: Jeremy Lavergne
Author-email: github@lavergne.me
Requires-Python: >=3.6,<4.0
Classifier: Programming Language :: Python :: 3
Classifier: Programming Language :: Python :: 3.6
Classifier: Programming Language :: Python :: 3.7
Classifier: Programming Language :: Python :: 3.8
Requires-Dist: click (>=7.1.2,<8.0.0)
Requires-Dist: jenkins-job-builder (>=3.5.0,<4.0.0)
Requires-Dist: jinja2 (>=2.11,<3.0)
Requires-Dist: python-jenkins (>=1.7.0,<2.0.0)
